README.md
edata.py
setup.py
edata.egg-info/PKG-INFO
edata.egg-info/SOURCES.txt
edata.egg-info/dependency_links.txt
edata.egg-info/requires.txt
edata.egg-info/top_level.txt