Metadata-Version: 2.1
Name: edata
Version: 0.0.1
Summary: edata means 'easy data', is a wrapper of csv, xlrd, xlwt, pylightxl
Home-page: https://gitee.com/lixkhao/edata
Author: Li Xiangkui
Author-email: 1749498702@qq.com
License: MIT Licence
Keywords: pip,edata
Platform: any
